[{"region_id":"state:OH","region_type":"state","geoid":39,"name":"Ohio","begin_year":1986,"end_year":1992,"begin_ag_acres":13626505.895948,"end_ag_acres":13506866.3660356,"gross_loss_acres":189709.250802416,"gross_gain_acres":70069.7208899891,"net_loss_acres":119639.529912427,"lost_to_development_acres":116997.256778942,"share_loss_to_development":0.616718775094399,"net_loss_rate":0.00877991253414445,"loss_to_dev21_acres":84207.5834746848,"loss_to_dev22_acres":24566.8463673438,"loss_to_dev23_acres":6560.20308825336,"loss_to_dev24_acres":1662.62384866032,"loss_to_grass71_acres":805.51412250504,"loss_to_other_acres":71906.479900969},{"region_id":"county:39001","region_type":"county","geoid":39001,"name":"Adams County","begin_year":1986,"end_year":1992,"begin_ag_acres":126344.956833369,"end_ag_acres":124961.438513075,"gross_loss_acres":1927.0513173678,"gross_gain_acres":543.53299707408,"net_loss_acres":1383.51832029372,"lost_to_development_acres":536.41636208784,"share_loss_to_development":0.278361223312175,"net_loss_rate":0.0109503248484891,"loss_to_dev21_acres":439.67460524364,"loss_to_dev22_acres":77.17101063204,"loss_to_dev23_acres":16.01242871904,"loss_to_dev24_acres":3.55831749312,"loss_to_grass71_acres":8.22860920284,"loss_to_other_acres":1382.40634607712},{"region_id":"county:39003","region_type":"county","geoid":39003,"name":"Allen County","begin_year":1986,"end_year":1992,"begin_ag_acres":191475.28825322,"end_ag_acres":190043.510251926,"gross_loss_acres":1603.91161002384,"gross_gain_acres":172.13360872968,"net_loss_acres":1431.77800129416,"lost_to_development_acres":1285.4421943896,"share_loss_to_development":0.801442041042707,"net_loss_rate":0.00747761246036447,"loss_to_dev21_acres":871.12060128444,"loss_to_dev22_acres":359.83485649176,"loss_to_dev23_acres":49.59405006036,"loss_to_dev24_acres":4.89268655304,"loss_to_grass71_acres":0.66718452996,"loss_to_other_acres":317.80223110428},{"region_id":"county:39005","region_type":"county","geoid":39005,"name":"Ashland County","begin_year":1986,"end_year":1992,"begin_ag_acres":162631.56665399,"end_ag_acres":161676.158407087,"gross_loss_acres":1304.56815091512,"gross_gain_acres":349.1599040124,"net_loss_acres":955.40824690272,"lost_to_development_acres":670.74284745312,"share_loss_to_development":0.514149335151722,"net_loss_rate":0.00587467898489486,"loss_to_dev21_acres":493.27176248376,"loss_to_dev22_acres":147.00299143452,"loss_to_dev23_acres":22.46187917532,"loss_to_dev24_acres":8.00621435952,"loss_to_grass71_acres":2.44634327652,"loss_to_other_acres":631.37896018548},{"region_id":"county:39007","region_type":"county","geoid":39007,"name":"Ashtabula County","begin_year":1986,"end_year":1992,"begin_ag_acres":160055.567183814,"end_ag_acres":156938.481059841,"gross_loss_acres":3566.1013126362,"gross_gain_acres":449.01518866308,"net_loss_acres":3117.08612397312,"lost_to_development_acres":1034.80320596796,"share_loss_to_development":0.290177736202058,"net_loss_rate":0.0194750246980996,"loss_to_dev21_acres":882.46273829376,"loss_to_dev22_acres":116.31250305636,"loss_to_dev23_acres":32.46964712472,"loss_to_dev24_acres":3.55831749312,"loss_to_grass71_acres":44.478968664,"loss_to_other_acres":2486.81913800424},{"region_id":"county:39009","region_type":"county","geoid":39009,"name":"Athens County","begin_year":1986,"end_year":1992,"begin_ag_acres":54425.3556366437,"end_ag_acres":53773.0715611861,"gross_loss_acres":1602.3548461206,"gross_gain_acres":950.07077066304,"net_loss_acres":652.28407545756,"lost_to_development_acres":476.59214923476,"share_loss_to_development":0.297432338653713,"net_loss_rate":0.0119849299619163,"loss_to_dev21_acres":399.86592828936,"loss_to_dev22_acres":45.5909428806,"loss_to_dev23_acres":20.68272042876,"loss_to_dev24_acres":10.45255763604,"loss_to_grass71_acres":8.45100404616,"loss_to_other_acres":1117.31169283968},{"region_id":"county:39011","region_type":"county","geoid":39011,"name":"Auglaize County","begin_year":1986,"end_year":1992,"begin_ag_acres":206803.852829051,"end_ag_acres":205583.572323755,"gross_loss_acres":1494.71574195372,"gross_gain_acres":274.43523665688,"net_loss_acres":1220.28050529684,"lost_to_development_acres":997.21847744688,"share_loss_to_development":0.667162624609433,"net_loss_rate":0.00590066620424887,"loss_to_dev21_acres":654.9528135774,"loss_to_dev22_acres":270.2097346338,"loss_to_dev23_acres":54.93152630004,"loss_to_dev24_acres":17.12440293564,"loss_to_grass71_acres":3.11352780648,"loss_to_other_acres":494.38373670036},{"region_id":"county:39013","region_type":"county","geoid":39013,"name":"Belmont County","begin_year":1986,"end_year":1992,"begin_ag_acres":100928.562164542,"end_ag_acres":102697.713143153,"gross_loss_acres":1364.83715345484,"gross_gain_acres":3133.98813206544,"net_loss_acres":-1769.1509786106,"lost_to_development_acres":475.9249647048,"share_loss_to_development":0.348704578784422,"net_loss_rate":-0.0175287444967895,"loss_to_dev21_acres":399.86592828936,"loss_to_dev22_acres":56.48829020328,"loss_to_dev23_acres":18.23637715224,"loss_to_dev24_acres":1.33436905992,"loss_to_grass71_acres":8.22860920284,"loss_to_other_acres":880.6835795472},{"region_id":"county:39015","region_type":"county","geoid":39015,"name":"Brown County","begin_year":1986,"end_year":1992,"begin_ag_acres":185141.483115467,"end_ag_acres":183084.330814757,"gross_loss_acres":2468.80515569532,"gross_gain_acres":411.65285498532,"net_loss_acres":2057.15230071,"lost_to_development_acres":1013.45330100924,"share_loss_to_development":0.410503558237997,"net_loss_rate":0.0111112445795145,"loss_to_dev21_acres":869.11904769456,"loss_to_dev22_acres":121.2051896094,"loss_to_dev23_acres":18.45877199556,"loss_to_dev24_acres":4.67029170972,"loss_to_grass71_acres":1.55676390324,"loss_to_other_acres":1453.79509078284},{"region_id":"county:39017","region_type":"county","geoid":39017,"name":"Butler County","begin_year":1986,"end_year":1992,"begin_ag_acres":159121.731236713,"end_ag_acres":153383.054699684,"gross_loss_acres":6083.83333386192,"gross_gain_acres":345.15679683264,"net_loss_acres":5738.67653702928,"lost_to_development_acres":5177.3519524896,"share_loss_to_development":0.851001608422284,"net_loss_rate":0.0360646939448659,"loss_to_dev21_acres":3712.65951438408,"loss_to_dev22_acres":984.31957653432,"loss_to_dev23_acres":365.39472757476,"loss_to_dev24_acres":114.97813399644,"loss_to_grass71_acres":7.33902982956,"loss_to_other_acres":899.14235154276},{"region_id":"county:39019","region_type":"county","geoid":39019,"name":"Carroll County","begin_year":1986,"end_year":1992,"begin_ag_acres":89786.1357245237,"end_ag_acres":90537.3855052586,"gross_loss_acres":1032.35686269144,"gross_gain_acres":1783.6066434264,"net_loss_acres":-751.24978073496,"lost_to_development_acres":452.35111131288,"share_loss_to_development":0.438173201206377,"net_loss_rate":-0.00836710227779374,"loss_to_dev21_acres":399.1987437594,"loss_to_dev22_acres":43.14459960408,"loss_to_dev23_acres":9.56297826276,"loss_to_dev24_acres":0.44478968664,"loss_to_grass71_acres":7.7838195162,"loss_to_other_acres":572.22193186236},{"region_id":"county:39021","region_type":"county","geoid":39021,"name":"Champaign County","begin_year":1986,"end_year":1992,"begin_ag_acres":218964.625256632,"end_ag_acres":216952.396714273,"gross_loss_acres":2318.466241611,"gross_gain_acres":306.23769925164,"net_loss_acres":2012.22854235936,"lost_to_development_acres":1022.79388442868,"share_loss_to_development":0.441151079136691,"net_loss_rate":0.00918974258970359,"loss_to_dev21_acres":822.860920284,"loss_to_dev22_acres":139.66396160496,"loss_to_dev23_acres":46.25812741056,"loss_to_dev24_acres":14.01087512916,"loss_to_grass71_acres":3.55831749312,"loss_to_other_acres":1292.1140396892},{"region_id":"county:39023","region_type":"county","geoid":39023,"name":"Clark County","begin_year":1986,"end_year":1992,"begin_ag_acres":180371.558515939,"end_ag_acres":178339.759227368,"gross_loss_acres":2279.54714403,"gross_gain_acres":247.74785545848,"net_loss_acres":2031.79928857152,"lost_to_development_acres":1640.60675917164,"share_loss_to_development":0.719707317073171,"net_loss_rate":0.0112645214427859,"loss_to_dev21_acres":1247.19028133856,"loss_to_dev22_acres":292.4492189658,"loss_to_dev23_acres":76.05903641544,"loss_to_dev24_acres":24.90822245184,"loss_to_grass71_acres":1.77915874656,"loss_to_other_acres":637.1612261118},{"region_id":"county:39025","region_type":"county","geoid":39025,"name":"Clermont County","begin_year":1986,"end_year":1992,"begin_ag_acres":108900.750113034,"end_ag_acres":106156.620141309,"gross_loss_acres":3309.2352686016,"gross_gain_acres":565.10529687612,"net_loss_acres":2744.12997172548,"lost_to_development_acres":1973.754234465,"share_loss_to_development":0.596438172043011,"net_loss_rate":0.0251984487607036,"loss_to_dev21_acres":1599.68610800076,"loss_to_dev22_acres":271.98889338036,"loss_to_dev23_acres":86.06680436484,"loss_to_dev24_acres":16.01242871904,"loss_to_grass71_acres":1.55676390324,"loss_to_other_acres":1333.92427023336},{"region_id":"county:39027","region_type":"county","geoid":39027,"name":"Clinton County","begin_year":1986,"end_year":1992,"begin_ag_acres":207092.966125367,"end_ag_acres":205957.418055376,"gross_loss_acres":1377.7360543674,"gross_gain_acres":242.18798437548,"net_loss_acres":1135.54806999192,"lost_to_development_acres":905.81419684236,"share_loss_to_development":0.657465698143664,"net_loss_rate":0.00548327686467389,"loss_to_dev21_acres":724.11760984992,"loss_to_dev22_acres":126.32027100576,"loss_to_dev23_acres":34.02641102796,"loss_to_dev24_acres":21.34990495872,"loss_to_grass71_acres":0.44478968664,"loss_to_other_acres":471.4770678384},{"region_id":"county:39029","region_type":"county","geoid":39029,"name":"Columbiana County","begin_year":1986,"end_year":1992,"begin_ag_acres":138779.497313076,"end_ag_acres":138162.351622863,"gross_loss_acres":2175.68875219956,"gross_gain_acres":1558.54306198656,"net_loss_acres":617.145690213,"lost_to_development_acres":1060.15621810644,"share_loss_to_development":0.487273842379638,"net_loss_rate":0.00444695147454501,"loss_to_dev21_acres":915.1547802618,"loss_to_dev22_acres":118.53645148956,"loss_to_dev23_acres":25.35301213848,"loss_to_dev24_acres":1.1119742166,"loss_to_grass71_acres":4.00310717976,"loss_to_other_acres":1111.52942691336},{"region_id":"county:39031","region_type":"county","geoid":39031,"name":"Coshocton County","begin_year":1986,"end_year":1992,"begin_ag_acres":124263.341099893,"end_ag_acres":126801.978236391,"gross_loss_acres":1232.95701136608,"gross_gain_acres":3771.59414786388,"net_loss_acres":-2538.6371364978,"lost_to_development_acres":380.73997176384,"share_loss_to_development":0.308802308802309,"net_loss_rate":-0.0204294936384901,"loss_to_dev21_acres":309.57362190144,"loss_to_dev22_acres":57.37786957656,"loss_to_dev23_acres":13.78848028584,"loss_to_dev24_acres":0,"loss_to_grass71_acres":8.00621435952,"loss_to_other_acres":844.21082524272},{"region_id":"county:39033","region_type":"county","geoid":39033,"name":"Crawford County","begin_year":1986,"end_year":1992,"begin_ag_acres":205359.175926845,"end_ag_acres":204758.709849881,"gross_loss_acres":860.00085911844,"gross_gain_acres":259.53478215444,"net_loss_acres":600.466076964,"lost_to_development_acres":527.29817351172,"share_loss_to_development":0.613136798551849,"net_loss_rate":0.0029239797747236,"loss_to_dev21_acres":403.6466406258,"loss_to_dev22_acres":107.63910416688,"loss_to_dev23_acres":15.12284934576,"loss_to_dev24_acres":0.88957937328,"loss_to_grass71_acres":2.2239484332,"loss_to_other_acres":330.47873717352},{"region_id":"county:39035","region_type":"county","geoid":39035,"name":"Cuyahoga County","begin_year":1986,"end_year":1992,"begin_ag_acres":5381.955208344,"end_ag_acres":4783.7130798132,"gross_loss_acres":787.05535050948,"gross_gain_acres":188.81322197868,"net_loss_acres":598.2421285308,"lost_to_development_acres":696.98543896488,"share_loss_to_development":0.885560892907601,"net_loss_rate":0.111157024793388,"loss_to_dev21_acres":478.59370282464,"loss_to_dev22_acres":125.20829678916,"loss_to_dev23_acres":88.06835795472,"loss_to_dev24_acres":5.11508139636,"loss_to_grass71_acres":4.00310717976,"loss_to_other_acres":86.06680436484},{"region_id":"county:39037","region_type":"county","geoid":39037,"name":"Darke County","begin_year":1986,"end_year":1992,"begin_ag_acres":323790.212260671,"end_ag_acres":322350.650439861,"gross_loss_acres":1900.14154132608,"gross_gain_acres":460.57972051572,"net_loss_acres":1439.56182081036,"lost_to_development_acres":1199.37539002476,"share_loss_to_development":0.631203183520599,"net_loss_rate":0.00444597077459347,"loss_to_dev21_acres":744.13314574872,"loss_to_dev22_acres":321.13815375408,"loss_to_dev23_acres":115.86771336972,"loss_to_dev24_acres":18.23637715224,"loss_to_grass71_acres":6.22705561296,"loss_to_other_acres":694.53909568836},{"region_id":"county:39039","region_type":"county","geoid":39039,"name":"Defiance County","begin_year":1986,"end_year":1992,"begin_ag_acres":203619.381067552,"end_ag_acres":201643.847674341,"gross_loss_acres":2227.72914553644,"gross_gain_acres":252.19575232488,"net_loss_acres":1975.53339321156,"lost_to_development_acres":845.98998398928,"share_loss_to_development":0.379754417490267,"net_loss_rate":0.00970208917664946,"loss_to_dev21_acres":384.52068410028,"loss_to_dev22_acres":395.64042626628,"loss_to_dev23_acres":64.27210971948,"loss_to_dev24_acres":1.55676390324,"loss_to_grass71_acres":19.34835136884,"loss_to_other_acres":1362.39081017832},{"region_id":"county:39041","region_type":"county","geoid":39041,"name":"Delaware County","begin_year":1986,"end_year":1992,"begin_ag_acres":192554.125638166,"end_ag_acres":187976.794972954,"gross_loss_acres":4820.18583411768,"gross_gain_acres":242.85516890544,"net_loss_acres":4577.33066521224,"lost_to_development_acres":4251.74461459176,"share_loss_to_development":0.882070683768571,"net_loss_rate":0.023771657190112,"loss_to_dev21_acres":3152.446904061,"loss_to_dev22_acres":907.3709607456,"loss_to_dev23_acres":169.90966029648,"loss_to_dev24_acres":22.01708948868,"loss_to_grass71_acres":2.89113296316,"loss_to_other_acres":565.55008656276},{"region_id":"county:39043","region_type":"county","geoid":39043,"name":"Erie County","begin_year":1986,"end_year":1992,"begin_ag_acres":94781.1239054909,"end_ag_acres":93280.1811079242,"gross_loss_acres":1675.7451444162,"gross_gain_acres":174.80234684952,"net_loss_acres":1500.94279756668,"lost_to_development_acres":1309.46083746816,"share_loss_to_development":0.7814200398142,"net_loss_rate":0.0158358830927487,"loss_to_dev21_acres":796.84072361556,"loss_to_dev22_acres":391.63731908652,"loss_to_dev23_acres":103.4136021438,"loss_to_dev24_acres":17.56919262228,"loss_to_grass71_acres":4.22550202308,"loss_to_other_acres":362.05880492496},{"region_id":"county:39045","region_type":"county","geoid":39045,"name":"Fairfield County","begin_year":1986,"end_year":1992,"begin_ag_acres":206359.952721785,"end_ag_acres":203460.813544265,"gross_loss_acres":3232.28665281288,"gross_gain_acres":333.14747529336,"net_loss_acres":2899.13917751952,"lost_to_development_acres":2272.43050904376,"share_loss_to_development":0.70304114490161,"net_loss_rate":0.0140489428267516,"loss_to_dev21_acres":1748.69065302516,"loss_to_dev22_acres":390.97013455656,"loss_to_dev23_acres":116.53489789968,"loss_to_dev24_acres":16.23482356236,"loss_to_grass71_acres":1.77915874656,"loss_to_other_acres":958.07698502256},{"region_id":"county:39047","region_type":"county","geoid":39047,"name":"Fayette County","begin_year":1986,"end_year":1992,"begin_ag_acres":228223.589768574,"end_ag_acres":227544.395917075,"gross_loss_acres":852.21703960224,"gross_gain_acres":173.02318810296,"net_loss_acres":679.19385149928,"lost_to_development_acres":609.80666038344,"share_loss_to_development":0.715553235908142,"net_loss_rate":0.0029760019645121,"loss_to_dev21_acres":461.02451020236,"loss_to_dev22_acres":113.64376493652,"loss_to_dev23_acres":28.9113296316,"loss_to_dev24_acres":6.22705561296,"loss_to_grass71_acres":0.44478968664,"loss_to_other_acres":241.96558953216},{"region_id":"county:39049","region_type":"county","geoid":39049,"name":"Franklin County","begin_year":1986,"end_year":1992,"begin_ag_acres":126281.574303022,"end_ag_acres":116420.36455537,"gross_loss_acres":10148.7662800649,"gross_gain_acres":287.55653241276,"net_loss_acres":9861.20974765212,"lost_to_development_acres":9616.3530251568,"share_loss_to_development":0.947539115571723,"net_loss_rate":0.0780890624944966,"loss_to_dev21_acres":6398.52203715972,"loss_to_dev22_acres":2152.7820833376,"loss_to_dev23_acres":843.54364071276,"loss_to_dev24_acres":221.50526394672,"loss_to_grass71_acres":5.559871083,"loss_to_other_acres":526.85338382508},{"region_id":"county:39051","region_type":"county","geoid":39051,"name":"Fulton County","begin_year":1986,"end_year":1992,"begin_ag_acres":217061.147792656,"end_ag_acres":215086.059189132,"gross_loss_acres":2273.987272947,"gross_gain_acres":298.89866942208,"net_loss_acres":1975.08860352492,"lost_to_development_acres":1405.75780462572,"share_loss_to_development":0.618190709046455,"net_loss_rate":0.00909922675527168,"loss_to_dev21_acres":859.5560694318,"loss_to_dev22_acres":410.76327561204,"loss_to_dev23_acres":100.30007433732,"loss_to_dev24_acres":35.13838524456,"loss_to_grass71_acres":12.67650606924,"loss_to_other_acres":855.55296225204},{"region_id":"county:39053","region_type":"county","geoid":39053,"name":"Gallia County","begin_year":1986,"end_year":1992,"begin_ag_acres":69384.0775880335,"end_ag_acres":69700.9902397645,"gross_loss_acres":2294.66999337576,"gross_gain_acres":2611.58264510676,"net_loss_acres":-316.912651731,"lost_to_development_acres":852.43943444556,"share_loss_to_development":0.371486722232991,"net_loss_rate":-0.00456751264479816,"loss_to_dev21_acres":678.08187728268,"loss_to_dev22_acres":131.2129575588,"loss_to_dev23_acres":32.69204196804,"loss_to_dev24_acres":10.45255763604,"loss_to_grass71_acres":7.7838195162,"loss_to_other_acres":1434.446739414},{"region_id":"county:39055","region_type":"county","geoid":39055,"name":"Geauga County","begin_year":1986,"end_year":1992,"begin_ag_acres":65729.9079174426,"end_ag_acres":63787.2889610424,"gross_loss_acres":2926.7161380912,"gross_gain_acres":984.097181691,"net_loss_acres":1942.6189564002,"lost_to_development_acres":1808.73726072156,"share_loss_to_development":0.618009118541034,"net_loss_rate":0.0295545668318925,"loss_to_dev21_acres":1479.37049776464,"loss_to_dev22_acres":247.9702503018,"loss_to_dev23_acres":62.04816128628,"loss_to_dev24_acres":19.34835136884,"loss_to_grass71_acres":6.00466076964,"loss_to_other_acres":1111.9742166},{"region_id":"county:39057","region_type":"county","geoid":39057,"name":"Greene County","begin_year":1986,"end_year":1992,"begin_ag_acres":175380.573442152,"end_ag_acres":172975.150816803,"gross_loss_acres":2644.71947676144,"gross_gain_acres":239.29685141232,"net_loss_acres":2405.42262534912,"lost_to_development_acres":2114.53017028656,"share_loss_to_development":0.799529095190044,"net_loss_rate":0.0137154450925691,"loss_to_dev21_acres":1569.21801446592,"loss_to_dev22_acres":349.38229885572,"loss_to_dev23_acres":137.66240801508,"loss_to_dev24_acres":58.26744894984,"loss_to_grass71_acres":6.22705561296,"loss_to_other_acres":523.96225086192},{"region_id":"county:39059","region_type":"county","geoid":39059,"name":"Guernsey County","begin_year":1986,"end_year":1992,"begin_ag_acres":93872.6409705287,"end_ag_acres":93639.1263850427,"gross_loss_acres":1760.03279003448,"gross_gain_acres":1526.51820454848,"net_loss_acres":233.514585486,"lost_to_development_acres":490.3806295206,"share_loss_to_development":0.278620166793025,"net_loss_rate":0.0024875680823693,"loss_to_dev21_acres":403.42424578248,"loss_to_dev22_acres":73.3902982956,"loss_to_dev23_acres":11.78692669596,"loss_to_dev24_acres":1.77915874656,"loss_to_grass71_acres":17.34679777896,"loss_to_other_acres":1252.30536273492},{"region_id":"county:39061","region_type":"county","geoid":39061,"name":"Hamilton County","begin_year":1986,"end_year":1992,"begin_ag_acres":27748.8717855664,"end_ag_acres":25854.7349050099,"gross_loss_acres":2230.84267334292,"gross_gain_acres":336.70579278648,"net_loss_acres":1894.13688055644,"lost_to_development_acres":1760.69997456444,"share_loss_to_development":0.789253314724355,"net_loss_rate":0.0682599600875189,"loss_to_dev21_acres":1329.47637336696,"loss_to_dev22_acres":253.5301213848,"loss_to_dev23_acres":101.63444339724,"loss_to_dev24_acres":76.05903641544,"loss_to_grass71_acres":14.01087512916,"loss_to_other_acres":456.13182364932},{"region_id":"county:39063","region_type":"county","geoid":39063,"name":"Hancock County","begin_year":1986,"end_year":1992,"begin_ag_acres":278723.00923609,"end_ag_acres":277370.403799017,"gross_loss_acres":1579.003387572,"gross_gain_acres":226.39795049976,"net_loss_acres":1352.60543707224,"lost_to_development_acres":1150.00373480772,"share_loss_to_development":0.72830985915493,"net_loss_rate":0.00485286607940763,"loss_to_dev21_acres":740.35243341228,"loss_to_dev22_acres":317.35744141764,"loss_to_dev23_acres":60.26900253972,"loss_to_dev24_acres":32.02485743808,"loss_to_grass71_acres":5.559871083,"loss_to_other_acres":423.43978168128},{"region_id":"county:39065","region_type":"county","geoid":39065,"name":"Hardin County","begin_year":1986,"end_year":1992,"begin_ag_acres":254574.265174187,"end_ag_acres":253718.489817092,"gross_loss_acres":1027.68657098172,"gross_gain_acres":171.91121388636,"net_loss_acres":855.77535709536,"lost_to_development_acres":616.47850568304,"share_loss_to_development":0.599870157974464,"net_loss_rate":0.00336159413642935,"loss_to_dev21_acres":455.46463911936,"loss_to_dev22_acres":120.53800507944,"loss_to_dev23_acres":29.57851416156,"loss_to_dev24_acres":10.89734732268,"loss_to_grass71_acres":0.88957937328,"loss_to_other_acres":410.3184859254},{"region_id":"county:39067","region_type":"county","geoid":39067,"name":"Harrison County","begin_year":1986,"end_year":1992,"begin_ag_acres":75407.8643141991,"end_ag_acres":76952.6188958998,"gross_loss_acres":707.88278628756,"gross_gain_acres":2252.63736798828,"net_loss_acres":-1544.75458170072,"lost_to_development_acres":192.14914462848,"share_loss_to_development":0.271442035815269,"net_loss_rate":-0.0204853246508116,"loss_to_dev21_acres":148.55975533776,"loss_to_dev22_acres":29.35611931824,"loss_to_dev23_acres":8.45100404616,"loss_to_dev24_acres":5.78226592632,"loss_to_grass71_acres":12.2317163826,"loss_to_other_acres":503.50192527648},{"region_id":"county:39069","region_type":"county","geoid":39069,"name":"Henry County","begin_year":1986,"end_year":1992,"begin_ag_acres":229348.240491243,"end_ag_acres":228162.653581504,"gross_loss_acres":1324.3612919706,"gross_gain_acres":138.77438223168,"net_loss_acres":1185.58690973892,"lost_to_development_acres":702.7677048912,"share_loss_to_development":0.530646515533165,"net_loss_rate":0.00516937434182839,"loss_to_dev21_acres":372.28896771768,"loss_to_dev22_acres":290.67006021924,"loss_to_dev23_acres":31.80246259476,"loss_to_dev24_acres":8.00621435952,"loss_to_grass71_acres":11.34213700932,"loss_to_other_acres":610.25145007008},{"region_id":"county:39071","region_type":"county","geoid":39071,"name":"Highland County","begin_year":1986,"end_year":1992,"begin_ag_acres":232454.20687305,"end_ag_acres":231025.764794406,"gross_loss_acres":1827.64082240376,"gross_gain_acres":399.1987437594,"net_loss_acres":1428.44207864436,"lost_to_development_acres":712.55307799728,"share_loss_to_development":0.389875882209783,"net_loss_rate":0.00614504722396559,"loss_to_dev21_acres":583.34167402836,"loss_to_dev22_acres":91.62667544784,"loss_to_dev23_acres":26.90977604172,"loss_to_dev24_acres":10.67495247936,"loss_to_grass71_acres":2.00155358988,"loss_to_other_acres":1113.0861908166},{"region_id":"county:39073","region_type":"county","geoid":39073,"name":"Hocking County","begin_year":1986,"end_year":1992,"begin_ag_acres":36116.0329757947,"end_ag_acres":36008.8386613145,"gross_loss_acres":879.12681564396,"gross_gain_acres":771.93250116372,"net_loss_acres":107.19431448024,"lost_to_development_acres":245.7463018686,"share_loss_to_development":0.27953453073615,"net_loss_rate":0.00296805340033006,"loss_to_dev21_acres":204.6032558544,"loss_to_dev22_acres":33.80401618464,"loss_to_dev23_acres":6.00466076964,"loss_to_dev24_acres":1.33436905992,"loss_to_grass71_acres":6.00466076964,"loss_to_other_acres":627.37585300572},{"region_id":"county:39075","region_type":"county","geoid":39075,"name":"Holmes County","begin_year":1986,"end_year":1992,"begin_ag_acres":143562.54320836,"end_ag_acres":143131.542002005,"gross_loss_acres":1243.40956900212,"gross_gain_acres":812.40836264796,"net_loss_acres":431.00120635416,"lost_to_development_acres":749.69301683172,"share_loss_to_development":0.602933285637632,"net_loss_rate":0.00300218425170015,"loss_to_dev21_acres":514.39927259916,"loss_to_dev22_acres":158.56752328716,"loss_to_dev23_acres":62.71534581624,"loss_to_dev24_acres":14.01087512916,"loss_to_grass71_acres":1.33436905992,"loss_to_other_acres":492.38218311048},{"region_id":"county:39077","region_type":"county","geoid":39077,"name":"Huron County","begin_year":1986,"end_year":1992,"begin_ag_acres":230861.192610349,"end_ag_acres":229592.874818895,"gross_loss_acres":1609.24908626352,"gross_gain_acres":340.93129480956,"net_loss_acres":1268.31779145396,"lost_to_development_acres":994.1049496404,"share_loss_to_development":0.617744610281924,"net_loss_rate":0.00549385445476168,"loss_to_dev21_acres":673.8563752596,"loss_to_dev22_acres":265.7618377674,"loss_to_dev23_acres":46.92531194052,"loss_to_dev24_acres":7.56142467288,"loss_to_grass71_acres":3.11352780648,"loss_to_other_acres":612.03060881664},{"region_id":"county:39079","region_type":"county","geoid":39079,"name":"Jackson County","begin_year":1986,"end_year":1992,"begin_ag_acres":63700.3325773043,"end_ag_acres":64251.6493938946,"gross_loss_acres":2538.6371364978,"gross_gain_acres":3089.95395308808,"net_loss_acres":-551.31681659028,"lost_to_development_acres":550.64963206032,"share_loss_to_development":0.216907577748576,"net_loss_rate":-0.00865484989299268,"loss_to_dev21_acres":399.42113860272,"loss_to_dev22_acres":82.73088171504,"loss_to_dev23_acres":57.15547473324,"loss_to_dev24_acres":11.34213700932,"loss_to_grass71_acres":15.34524418908,"loss_to_other_acres":1972.6422602484},{"region_id":"county:39081","region_type":"county","geoid":39081,"name":"Jefferson County","begin_year":1986,"end_year":1992,"begin_ag_acres":57636.5147793412,"end_ag_acres":58912.1716006247,"gross_loss_acres":597.35254915752,"gross_gain_acres":1873.00937044104,"net_loss_acres":-1275.65682128352,"lost_to_development_acres":234.84895454592,"share_loss_to_development":0.393149664929263,"net_loss_rate":-0.0221327890169507,"loss_to_dev21_acres":174.13516231956,"loss_to_dev22_acres":40.47586148424,"loss_to_dev23_acres":18.9035616822,"loss_to_dev24_acres":1.33436905992,"loss_to_grass71_acres":6.44945045628,"loss_to_other_acres":356.05414415532},{"region_id":"county:39083","region_type":"county","geoid":39083,"name":"Knox County","begin_year":1986,"end_year":1992,"begin_ag_acres":198941.972722846,"end_ag_acres":197990.789977966,"gross_loss_acres":1538.08273640112,"gross_gain_acres":586.89999152148,"net_loss_acres":951.18274487964,"lost_to_development_acres":760.36796931108,"share_loss_to_development":0.494360902255639,"net_loss_rate":0.00478120696131213,"loss_to_dev21_acres":634.49248799196,"loss_to_dev22_acres":110.53023713004,"loss_to_dev23_acres":15.34524418908,"loss_to_dev24_acres":0,"loss_to_grass71_acres":2.00155358988,"loss_to_other_acres":775.71321350016},{"region_id":"county:39085","region_type":"county","geoid":39085,"name":"Lake County","begin_year":1986,"end_year":1992,"begin_ag_acres":19745.7709538528,"end_ag_acres":18987.1821432883,"gross_loss_acres":1444.00971767676,"gross_gain_acres":685.42090711224,"net_loss_acres":758.58881056452,"lost_to_development_acres":1084.174861185,"share_loss_to_development":0.750808563067919,"net_loss_rate":0.0384177863876468,"loss_to_dev21_acres":758.14402087788,"loss_to_dev22_acres":257.08843887792,"loss_to_dev23_acres":67.16324268264,"loss_to_dev24_acres":1.77915874656,"loss_to_grass71_acres":36.25035946116,"loss_to_other_acres":323.5844970306},{"region_id":"county:39087","region_type":"county","geoid":39087,"name":"Lawrence County","begin_year":1986,"end_year":1992,"begin_ag_acres":26865.964257586,"end_ag_acres":27632.1144928234,"gross_loss_acres":1015.45485459912,"gross_gain_acres":1781.60508983652,"net_loss_acres":-766.1502352374,"lost_to_development_acres":374.06812646424,"share_loss_to_development":0.368374945247481,"net_loss_rate":-0.0285175037043782,"loss_to_dev21_acres":324.91886609052,"loss_to_dev22_acres":30.69048837816,"loss_to_dev23_acres":15.12284934576,"loss_to_dev24_acres":3.3359226498,"loss_to_grass71_acres":10.89734732268,"loss_to_other_acres":630.4893808122},{"region_id":"county:39089","region_type":"county","geoid":39089,"name":"Licking County","begin_year":1986,"end_year":1992,"begin_ag_acres":237272.613548421,"end_ag_acres":234373.919160589,"gross_loss_acres":3523.40150271876,"gross_gain_acres":624.70711488588,"net_loss_acres":2898.69438783288,"lost_to_development_acres":2081.83812831852,"share_loss_to_development":0.590860316859181,"net_loss_rate":0.0122167254976577,"loss_to_dev21_acres":1672.18682692308,"loss_to_dev22_acres":286.22216335284,"loss_to_dev23_acres":80.72932812516,"loss_to_dev24_acres":42.69980991744,"loss_to_grass71_acres":4.4478968664,"loss_to_other_acres":1437.11547753384},{"region_id":"county:39091","region_type":"county","geoid":39091,"name":"Logan County","begin_year":1986,"end_year":1992,"begin_ag_acres":215996.766072527,"end_ag_acres":214063.04290986,"gross_loss_acres":2377.62326993412,"gross_gain_acres":443.90010726672,"net_loss_acres":1933.7231626674,"lost_to_development_acres":1302.56659732524,"share_loss_to_development":0.54784398091853,"net_loss_rate":0.00895255608603926,"loss_to_dev21_acres":758.58881056452,"loss_to_dev22_acres":264.42746870748,"loss_to_dev23_acres":165.46176343008,"loss_to_dev24_acres":114.08855462316,"loss_to_grass71_acres":2.00155358988,"loss_to_other_acres":1073.055119019},{"region_id":"county:39093","region_type":"county","geoid":39093,"name":"Lorain County","begin_year":1986,"end_year":1992,"begin_ag_acres":151691.297126549,"end_ag_acres":147395.073543293,"gross_loss_acres":4614.02581436004,"gross_gain_acres":317.80223110428,"net_loss_acres":4296.22358325576,"lost_to_development_acres":3934.38717317412,"share_loss_to_development":0.852701595411385,"net_loss_rate":0.0283221494221361,"loss_to_dev21_acres":2703.43171539792,"loss_to_dev22_acres":967.63996328532,"loss_to_dev23_acres":235.29374423256,"loss_to_dev24_acres":28.02175025832,"loss_to_grass71_acres":1.55676390324,"loss_to_other_acres":678.08187728268},{"region_id":"county:39095","region_type":"county","geoid":39095,"name":"Lucas County","begin_year":1986,"end_year":1992,"begin_ag_acres":86278.3018608373,"end_ag_acres":80272.9739066674,"gross_loss_acres":6197.69949364176,"gross_gain_acres":192.3715394718,"net_loss_acres":6005.32795416996,"lost_to_development_acres":4055.81475762684,"share_loss_to_development":0.65440648772786,"net_loss_rate":0.0696041510396932,"loss_to_dev21_acres":2370.06184526124,"loss_to_dev22_acres":1412.87443961196,"loss_to_dev23_acres":244.85672249532,"loss_to_dev24_acres":28.02175025832,"loss_to_grass71_acres":130.76816787216,"loss_to_other_acres":2011.11656814276},{"region_id":"county:39097","region_type":"county","geoid":39097,"name":"Madison County","begin_year":1986,"end_year":1992,"begin_ag_acres":262828.672178853,"end_ag_acres":261913.517398591,"gross_loss_acres":1035.69278534124,"gross_gain_acres":120.53800507944,"net_loss_acres":915.1547802618,"lost_to_development_acres":709.4395501908,"share_loss_to_development":0.684990337126906,"net_loss_rate":0.00348194423643036,"loss_to_dev21_acres":522.85027664532,"loss_to_dev22_acres":131.43535240212,"loss_to_dev23_acres":39.58628211096,"loss_to_dev24_acres":15.5676390324,"loss_to_grass71_acres":0.44478968664,"loss_to_other_acres":325.8084454638},{"region_id":"county:39099","region_type":"county","geoid":39099,"name":"Mahoning County","begin_year":1986,"end_year":1992,"begin_ag_acres":96016.7496549768,"end_ag_acres":93567.070455807,"gross_loss_acres":3095.7362190144,"gross_gain_acres":646.0570198446,"net_loss_acres":2449.6791991698,"lost_to_development_acres":1606.35795330036,"share_loss_to_development":0.51889367816092,"net_loss_rate":0.0255130402557095,"loss_to_dev21_acres":1331.70032180016,"loss_to_dev22_acres":221.06047426008,"loss_to_dev23_acres":46.7029170972,"loss_to_dev24_acres":6.89424014292,"loss_to_grass71_acres":6.22705561296,"loss_to_other_acres":1483.15121010108},{"region_id":"county:39101","region_type":"county","geoid":39101,"name":"Marion County","begin_year":1986,"end_year":1992,"begin_ag_acres":207421.665703794,"end_ag_acres":206392.644763753,"gross_loss_acres":1294.3379881224,"gross_gain_acres":265.31704808076,"net_loss_acres":1029.02094004164,"lost_to_development_acres":711.21870893736,"share_loss_to_development":0.549484536082474,"net_loss_rate":0.00496100991451452,"loss_to_dev21_acres":555.9871083,"loss_to_dev22_acres":118.75884633288,"loss_to_dev23_acres":31.1352780648,"loss_to_dev24_acres":5.33747623968,"loss_to_grass71_acres":2.44634327652,"loss_to_other_acres":580.67293590852},{"region_id":"county:39103","region_type":"county","geoid":39103,"name":"Medina County","begin_year":1986,"end_year":1992,"begin_ag_acres":136798.848838468,"end_ag_acres":133287.901446976,"gross_loss_acres":3949.06523283324,"gross_gain_acres":438.1178413404,"net_loss_acres":3510.94739149284,"lost_to_development_acres":2756.80647779472,"share_loss_to_development":0.698090893732049,"net_loss_rate":0.0256650360825664,"loss_to_dev21_acres":1940.83979765364,"loss_to_dev22_acres":603.8019996138,"loss_to_dev23_acres":171.02163451308,"loss_to_dev24_acres":41.1430460142,"loss_to_grass71_acres":2.66873811984,"loss_to_other_acres":1189.59001691868},{"region_id":"county:39105","region_type":"county","geoid":39105,"name":"Meigs County","begin_year":1986,"end_year":1992,"begin_ag_acres":55067.4095493085,"end_ag_acres":54389.5500668692,"gross_loss_acres":1733.79019852272,"gross_gain_acres":1055.93071608336,"net_loss_acres":677.85948243936,"lost_to_development_acres":320.69336406744,"share_loss_to_development":0.184966649563879,"net_loss_rate":0.0123096308322328,"loss_to_dev21_acres":288.22371694272,"loss_to_dev22_acres":27.35456572836,"loss_to_dev23_acres":5.11508139636,"loss_to_dev24_acres":0,"loss_to_grass71_acres":15.5676390324,"loss_to_other_acres":1397.52919542288},{"region_id":"county:39107","region_type":"county","geoid":39107,"name":"Mercer County","begin_year":1986,"end_year":1992,"begin_ag_acres":247492.768573192,"end_ag_acres":246306.736873766,"gross_loss_acres":1474.25541636828,"gross_gain_acres":288.22371694272,"net_loss_acres":1186.03169942556,"lost_to_development_acres":1038.13912861776,"share_loss_to_development":0.70417860914165,"net_loss_rate":0.00479218728798862,"loss_to_dev21_acres":562.21416391296,"loss_to_dev22_acres":316.24546720104,"loss_to_dev23_acres":149.89412439768,"loss_to_dev24_acres":9.78537310608,"loss_to_grass71_acres":2.00155358988,"loss_to_other_acres":434.11473416064},{"region_id":"county:39109","region_type":"county","geoid":39109,"name":"Miami County","begin_year":1986,"end_year":1992,"begin_ag_acres":198603.26537647,"end_ag_acres":197073.633644115,"gross_loss_acres":1738.46049023244,"gross_gain_acres":208.82875787748,"net_loss_acres":1529.63173235496,"lost_to_development_acres":1457.13101343264,"share_loss_to_development":0.838173212229756,"net_loss_rate":0.00770194653877121,"loss_to_dev21_acres":1134.213700932,"loss_to_dev22_acres":247.52546061516,"loss_to_dev23_acres":46.25812741056,"loss_to_dev24_acres":29.13372447492,"loss_to_grass71_acres":8.67339888948,"loss_to_other_acres":272.65607791032},{"region_id":"county:39111","region_type":"county","geoid":39111,"name":"Monroe County","begin_year":1986,"end_year":1992,"begin_ag_acres":47478.1855210135,"end_ag_acres":47246.4500942741,"gross_loss_acres":757.47683634792,"gross_gain_acres":525.74140960848,"net_loss_acres":231.73542673944,"lost_to_development_acres":196.37464665156,"share_loss_to_development":0.259248385202584,"net_loss_rate":0.00488088211873378,"loss_to_dev21_acres":173.4679777896,"loss_to_dev22_acres":17.12440293564,"loss_to_dev23_acres":5.33747623968,"loss_to_dev24_acres":0.44478968664,"loss_to_grass71_acres":8.45100404616,"loss_to_other_acres":552.6511856502},{"region_id":"county:39113","region_type":"county","geoid":39113,"name":"Montgomery County","begin_year":1986,"end_year":1992,"begin_ag_acres":130736.143014722,"end_ag_acres":127075.523893675,"gross_loss_acres":3911.9252939988,"gross_gain_acres":251.3061729516,"net_loss_acres":3660.6191210472,"lost_to_development_acres":3272.76251429712,"share_loss_to_development":0.836611711199545,"net_loss_rate":0.0280000544350998,"loss_to_dev21_acres":2401.864307856,"loss_to_dev22_acres":635.38206736524,"loss_to_dev23_acres":195.7074621216,"loss_to_dev24_acres":39.80867695428,"loss_to_grass71_acres":8.00621435952,"loss_to_other_acres":631.15656534216},{"region_id":"county:39115","region_type":"county","geoid":39115,"name":"Morgan County","begin_year":1986,"end_year":1992,"begin_ag_acres":58005.2454295657,"end_ag_acres":58194.9482309177,"gross_loss_acres":738.79566950904,"gross_gain_acres":928.498470861,"net_loss_acres":-189.70280135196,"lost_to_development_acres":133.21451114868,"share_loss_to_development":0.180313064419025,"net_loss_rate":-0.00327044218065263,"loss_to_dev21_acres":110.53023713004,"loss_to_dev22_acres":16.23482356236,"loss_to_dev23_acres":6.22705561296,"loss_to_dev24_acres":0.22239484332,"loss_to_grass71_acres":6.00466076964,"loss_to_other_acres":599.57649759072},{"region_id":"county:39117","region_type":"county","geoid":39117,"name":"Morrow County","begin_year":1986,"end_year":1992,"begin_ag_acres":178449.399885125,"end_ag_acres":177593.179738343,"gross_loss_acres":1131.32256796884,"gross_gain_acres":275.10242118684,"net_loss_acres":856.220146782,"lost_to_development_acres":489.49105014732,"share_loss_to_development":0.432671515628072,"net_loss_rate":0.00479811166265162,"loss_to_dev21_acres":386.74463253348,"loss_to_dev22_acres":89.18033217132,"loss_to_dev23_acres":13.56608544252,"loss_to_dev24_acres":0,"loss_to_grass71_acres":2.89113296316,"loss_to_other_acres":638.94038485836},{"region_id":"county:39119","region_type":"county","geoid":39119,"name":"Muskingum County","begin_year":1986,"end_year":1992,"begin_ag_acres":140653.396262891,"end_ag_acres":141722.44827473,"gross_loss_acres":2292.22365009924,"gross_gain_acres":3361.27566193848,"net_loss_acres":-1069.05201183924,"lost_to_development_acres":912.48604214196,"share_loss_to_development":0.398078975453575,"net_loss_rate":-0.00760061285574015,"loss_to_dev21_acres":768.59657851392,"loss_to_dev22_acres":104.08078667376,"loss_to_dev23_acres":34.69359555792,"loss_to_dev24_acres":5.11508139636,"loss_to_grass71_acres":18.45877199556,"loss_to_other_acres":1361.27883596172},{"region_id":"county:39121","region_type":"county","geoid":39121,"name":"Noble County","begin_year":1986,"end_year":1992,"begin_ag_acres":54910.6211847679,"end_ag_acres":58126.2282243318,"gross_loss_acres":1030.57770394488,"gross_gain_acres":4246.18474350876,"net_loss_acres":-3215.60703956388,"lost_to_development_acres":208.82875787748,"share_loss_to_development":0.202632714717307,"net_loss_rate":-0.0585607478149579,"loss_to_dev21_acres":174.5799520062,"loss_to_dev22_acres":26.90977604172,"loss_to_dev23_acres":7.33902982956,"loss_to_dev24_acres":0,"loss_to_grass71_acres":7.33902982956,"loss_to_other_acres":814.40991623784},{"region_id":"county:39123","region_type":"county","geoid":39123,"name":"Ottawa County","begin_year":1986,"end_year":1992,"begin_ag_acres":107827.027809485,"end_ag_acres":106199.987135756,"gross_loss_acres":1991.99061161724,"gross_gain_acres":364.94993788812,"net_loss_acres":1627.04067372912,"lost_to_development_acres":1439.11703112372,"share_loss_to_development":0.722451713743441,"net_loss_rate":0.0150893584547639,"loss_to_dev21_acres":714.9994212738,"loss_to_dev22_acres":556.20950314332,"loss_to_dev23_acres":154.34202126408,"loss_to_dev24_acres":13.56608544252,"loss_to_grass71_acres":11.78692669596,"loss_to_other_acres":541.08665379756},{"region_id":"county:39125","region_type":"county","geoid":39125,"name":"Paulding County","begin_year":1986,"end_year":1992,"begin_ag_acres":227105.388496361,"end_ag_acres":226183.117081113,"gross_loss_acres":1124.2059329826,"gross_gain_acres":201.93451773456,"net_loss_acres":922.27141524804,"lost_to_development_acres":483.48638937768,"share_loss_to_development":0.430069238377844,"net_loss_rate":0.00406098429171714,"loss_to_dev21_acres":189.70280135196,"loss_to_dev22_acres":231.2906370528,"loss_to_dev23_acres":58.71223863648,"loss_to_dev24_acres":3.78071233644,"loss_to_grass71_acres":4.89268655304,"loss_to_other_acres":635.82685705188},{"region_id":"county:39127","region_type":"county","geoid":39127,"name":"Perry County","begin_year":1986,"end_year":1992,"begin_ag_acres":81156.9934088644,"end_ag_acres":81763.2417517547,"gross_loss_acres":1026.12980707848,"gross_gain_acres":1632.3781499688,"net_loss_acres":-606.24834289032,"lost_to_development_acres":327.36520936704,"share_loss_to_development":0.319029042045947,"net_loss_rate":-0.00747006902826076,"loss_to_dev21_acres":277.10397477672,"loss_to_dev22_acres":42.2550202308,"loss_to_dev23_acres":7.56142467288,"loss_to_dev24_acres":0.44478968664,"loss_to_grass71_acres":7.7838195162,"loss_to_other_acres":690.98077819524},{"region_id":"county:39129","region_type":"county","geoid":39129,"name":"Pickaway County","begin_year":1986,"end_year":1992,"begin_ag_acres":266755.497927354,"end_ag_acres":265758.724239594,"gross_loss_acres":1199.15299518144,"gross_gain_acres":202.3793074212,"net_loss_acres":996.77368776024,"lost_to_development_acres":805.0693328184,"share_loss_to_development":0.671364985163205,"net_loss_rate":0.00373665658441909,"loss_to_dev21_acres":638.71799001504,"loss_to_dev22_acres":149.44933471104,"loss_to_dev23_acres":14.90045450244,"loss_to_dev24_acres":2.00155358988,"loss_to_grass71_acres":1.1119742166,"loss_to_other_acres":392.97168814644},{"region_id":"county:39131","region_type":"county","geoid":39131,"name":"Pike County","begin_year":1986,"end_year":1992,"begin_ag_acres":70881.0172784205,"end_ag_acres":70623.2616550126,"gross_loss_acres":1021.23712052544,"gross_gain_acres":763.48149711756,"net_loss_acres":257.75562340788,"lost_to_development_acres":351.60624728892,"share_loss_to_development":0.344294425087108,"net_loss_rate":0.00363645491141044,"loss_to_dev21_acres":251.97335748156,"loss_to_dev22_acres":51.81799849356,"loss_to_dev23_acres":17.56919262228,"loss_to_dev24_acres":30.24569869152,"loss_to_grass71_acres":22.90666886196,"loss_to_other_acres":646.72420437456},{"region_id":"county:39133","region_type":"county","geoid":39133,"name":"Portage County","begin_year":1986,"end_year":1992,"begin_ag_acres":110890.739171062,"end_ag_acres":107955.572028924,"gross_loss_acres":3869.44787892468,"gross_gain_acres":934.28073678732,"net_loss_acres":2935.16714213736,"lost_to_development_acres":2055.59553680676,"share_loss_to_development":0.531237427438359,"net_loss_rate":0.026469001506154,"loss_to_dev21_acres":1681.97220002916,"loss_to_dev22_acres":290.67006021924,"loss_to_dev23_acres":73.61269313892,"loss_to_dev24_acres":9.34058341944,"loss_to_grass71_acres":14.67805965912,"loss_to_other_acres":1799.1742824588},{"region_id":"county:39135","region_type":"county","geoid":39135,"name":"Preble County","begin_year":1986,"end_year":1992,"begin_ag_acres":206210.94817676,"end_ag_acres":205116.098363096,"gross_loss_acres":1378.62563374068,"gross_gain_acres":283.77582007632,"net_loss_acres":1094.84981366436,"lost_to_development_acres":669.63087323652,"share_loss_to_development":0.485723503790934,"net_loss_rate":0.00530936802019782,"loss_to_dev21_acres":533.30283428136,"loss_to_dev22_acres":103.63599698712,"loss_to_dev23_acres":24.68582760852,"loss_to_dev24_acres":8.00621435952,"loss_to_grass71_acres":1.77915874656,"loss_to_other_acres":707.2156017576},{"region_id":"county:39137","region_type":"county","geoid":39137,"name":"Putnam County","begin_year":1986,"end_year":1992,"begin_ag_acres":268364.747013617,"end_ag_acres":267185.609554335,"gross_loss_acres":1399.75314385608,"gross_gain_acres":220.61568457344,"net_loss_acres":1179.13745928264,"lost_to_development_acres":863.11438692492,"share_loss_to_development":0.616619002224341,"net_loss_rate":0.00439378671157136,"loss_to_dev21_acres":488.82386561736,"loss_to_dev22_acres":326.25323515044,"loss_to_dev23_acres":46.92531194052,"loss_to_dev24_acres":1.1119742166,"loss_to_grass71_acres":3.11352780648,"loss_to_other_acres":533.52522912468},{"region_id":"county:39139","region_type":"county","geoid":39139,"name":"Richland County","begin_year":1986,"end_year":1992,"begin_ag_acres":171726.626166404,"end_ag_acres":170293.958585737,"gross_loss_acres":1960.4105438658,"gross_gain_acres":527.74296319836,"net_loss_acres":1432.66758066744,"lost_to_development_acres":1218.27895170696,"share_loss_to_development":0.621440726035167,"net_loss_rate":0.00834272245748993,"loss_to_dev21_acres":925.38494305452,"loss_to_dev22_acres":243.74474827872,"loss_to_dev23_acres":42.03262538748,"loss_to_dev24_acres":7.11663498624,"loss_to_grass71_acres":0.88957937328,"loss_to_other_acres":741.24201278556},{"region_id":"county:39141","region_type":"county","geoid":39141,"name":"Ross County","begin_year":1986,"end_year":1992,"begin_ag_acres":202569.455012239,"end_ag_acres":201513.746690999,"gross_loss_acres":1692.86954735184,"gross_gain_acres":637.1612261118,"net_loss_acres":1055.70832124004,"lost_to_development_acres":780.38350520988,"share_loss_to_development":0.460982658959538,"net_loss_rate":0.0052115869155903,"loss_to_dev21_acres":636.93883126848,"loss_to_dev22_acres":118.09166180292,"loss_to_dev23_acres":17.56919262228,"loss_to_dev24_acres":7.7838195162,"loss_to_grass71_acres":4.22550202308,"loss_to_other_acres":908.26054011888},{"region_id":"county:39143","region_type":"county","geoid":39143,"name":"Sandusky County","begin_year":1986,"end_year":1992,"begin_ag_acres":200802.083192375,"end_ag_acres":199338.057938799,"gross_loss_acres":1709.99395028748,"gross_gain_acres":245.96869671192,"net_loss_acres":1464.02525357556,"lost_to_development_acres":1026.3522019218,"share_loss_to_development":0.600208089478476,"net_loss_rate":0.00729088677916244,"loss_to_dev21_acres":620.4816128628,"loss_to_dev22_acres":335.14902888324,"loss_to_dev23_acres":54.70913145672,"loss_to_dev24_acres":16.01242871904,"loss_to_grass71_acres":33.58162134132,"loss_to_other_acres":650.06012702436},{"region_id":"county:39145","region_type":"county","geoid":39145,"name":"Scioto County","begin_year":1986,"end_year":1992,"begin_ag_acres":70293.6724972123,"end_ag_acres":69828.4224849869,"gross_loss_acres":1620.1464335862,"gross_gain_acres":1154.89642136076,"net_loss_acres":465.25001222544,"lost_to_development_acres":643.61067656808,"share_loss_to_development":0.397254632807138,"net_loss_rate":0.00661866133461573,"loss_to_dev21_acres":537.0835466178,"loss_to_dev22_acres":82.2860920284,"loss_to_dev23_acres":19.79314105548,"loss_to_dev24_acres":4.4478968664,"loss_to_grass71_acres":11.119742166,"loss_to_other_acres":965.41601485212},{"region_id":"county:39147","region_type":"county","geoid":39147,"name":"Seneca County","begin_year":1986,"end_year":1992,"begin_ag_acres":283278.322811813,"end_ag_acres":282230.843099776,"gross_loss_acres":1341.26330006292,"gross_gain_acres":293.78358802572,"net_loss_acres":1047.4797120372,"lost_to_development_acres":810.85159874472,"share_loss_to_development":0.604543193500249,"net_loss_rate":0.00369770514609076,"loss_to_dev21_acres":493.27176248376,"loss_to_dev22_acres":257.53322856456,"loss_to_dev23_acres":42.03262538748,"loss_to_dev24_acres":18.01398230892,"loss_to_grass71_acres":3.55831749312,"loss_to_other_acres":526.85338382508},{"region_id":"county:39149","region_type":"county","geoid":39149,"name":"Shelby County","begin_year":1986,"end_year":1992,"begin_ag_acres":207763.041788291,"end_ag_acres":206479.156357804,"gross_loss_acres":1539.41710546104,"gross_gain_acres":255.53167497468,"net_loss_acres":1283.88543048636,"lost_to_development_acres":1038.80631314772,"share_loss_to_development":0.674804969661947,"net_loss_rate":0.00617956600671371,"loss_to_dev21_acres":670.74284745312,"loss_to_dev22_acres":238.85206172568,"loss_to_dev23_acres":75.39185188548,"loss_to_dev24_acres":53.81955208344,"loss_to_grass71_acres":5.559871083,"loss_to_other_acres":495.05092123032},{"region_id":"county:39151","region_type":"county","geoid":39151,"name":"Stark County","begin_year":1986,"end_year":1992,"begin_ag_acres":161733.758671507,"end_ag_acres":158926.913353965,"gross_loss_acres":4293.55484513592,"gross_gain_acres":1486.7095275942,"net_loss_acres":2806.84531754172,"lost_to_development_acres":3347.70957649596,"share_loss_to_development":0.77970579094582,"net_loss_rate":0.0173547275509909,"loss_to_dev21_acres":2775.71003947692,"loss_to_dev22_acres":494.60613154368,"loss_to_dev23_acres":63.82732003284,"loss_to_dev24_acres":13.56608544252,"loss_to_grass71_acres":9.11818857612,"loss_to_other_acres":936.72708006384},{"region_id":"county:39153","region_type":"county","geoid":39153,"name":"Summit County","begin_year":1986,"end_year":1992,"begin_ag_acres":30498.7840232182,"end_ag_acres":27587.413129316,"gross_loss_acres":3569.437235286,"gross_gain_acres":658.06634138388,"net_loss_acres":2911.37089390212,"lost_to_development_acres":3108.85751477028,"share_loss_to_development":0.870965732087228,"net_loss_rate":0.095458589158366,"loss_to_dev21_acres":2405.86741503576,"loss_to_dev22_acres":537.0835466178,"loss_to_dev23_acres":148.55975533776,"loss_to_dev24_acres":17.34679777896,"loss_to_grass71_acres":16.01242871904,"loss_to_other_acres":444.56729179668},{"region_id":"county:39155","region_type":"county","geoid":39155,"name":"Trumbull County","begin_year":1986,"end_year":1992,"begin_ag_acres":131704.894952224,"end_ag_acres":128816.430727184,"gross_loss_acres":3572.32836824916,"gross_gain_acres":683.864143209,"net_loss_acres":2888.46422504016,"lost_to_development_acres":1556.76390324,"share_loss_to_development":0.435784100105833,"net_loss_rate":0.0219313354001608,"loss_to_dev21_acres":1321.69255385076,"loss_to_dev22_acres":175.91432106612,"loss_to_dev23_acres":43.3669944474,"loss_to_dev24_acres":15.79003387572,"loss_to_grass71_acres":16.45721840568,"loss_to_other_acres":1999.10724660348},{"region_id":"county:39157","region_type":"county","geoid":39157,"name":"Tuscarawas County","begin_year":1986,"end_year":1992,"begin_ag_acres":117255.234797193,"end_ag_acres":119222.317186359,"gross_loss_acres":1681.74980518584,"gross_gain_acres":3648.83219435124,"net_loss_acres":-1967.0823891654,"lost_to_development_acres":960.07853861244,"share_loss_to_development":0.570880719386406,"net_loss_rate":-0.0167760730901925,"loss_to_dev21_acres":767.70699914064,"loss_to_dev22_acres":144.556648158,"loss_to_dev23_acres":36.02796461784,"loss_to_dev24_acres":11.78692669596,"loss_to_grass71_acres":14.67805965912,"loss_to_other_acres":706.99320691428},{"region_id":"county:39159","region_type":"county","geoid":39159,"name":"Union County","begin_year":1986,"end_year":1992,"begin_ag_acres":227265.290388708,"end_ag_acres":224956.38712536,"gross_loss_acres":2587.34160718488,"gross_gain_acres":278.43834383664,"net_loss_acres":2308.90326334824,"lost_to_development_acres":1796.50554433896,"share_loss_to_development":0.694344163658243,"net_loss_rate":0.0101595068010569,"loss_to_dev21_acres":1212.051896094,"loss_to_dev22_acres":367.61867600796,"loss_to_dev23_acres":169.90966029648,"loss_to_dev24_acres":46.92531194052,"loss_to_grass71_acres":3.11352780648,"loss_to_other_acres":787.72253503944},{"region_id":"county:39161","region_type":"county","geoid":39161,"name":"Van Wert County","begin_year":1986,"end_year":1992,"begin_ag_acres":229827.723773441,"end_ag_acres":229346.238937653,"gross_loss_acres":663.40381762356,"gross_gain_acres":181.91898183576,"net_loss_acres":481.4848357878,"lost_to_development_acres":481.92962547444,"share_loss_to_development":0.726449882668455,"net_loss_rate":0.00209498152739152,"loss_to_dev21_acres":266.20662745404,"loss_to_dev22_acres":181.47419214912,"loss_to_dev23_acres":26.24259151176,"loss_to_dev24_acres":8.00621435952,"loss_to_grass71_acres":1.1119742166,"loss_to_other_acres":180.36221793252},{"region_id":"county:39163","region_type":"county","geoid":39163,"name":"Vinton County","begin_year":1986,"end_year":1992,"begin_ag_acres":31338.9917412811,"end_ag_acres":32194.5447035332,"gross_loss_acres":1092.18107554452,"gross_gain_acres":1947.73403779656,"net_loss_acres":-855.55296225204,"lost_to_development_acres":130.32337818552,"share_loss_to_development":0.119323966605579,"net_loss_rate":-0.0272999517443016,"loss_to_dev21_acres":104.5255763604,"loss_to_dev22_acres":16.679613249,"loss_to_dev23_acres":9.11818857612,"loss_to_dev24_acres":0,"loss_to_grass71_acres":22.68427401864,"loss_to_other_acres":939.17342334036},{"region_id":"county:39165","region_type":"county","geoid":39165,"name":"Warren County","begin_year":1986,"end_year":1992,"begin_ag_acres":144146.329672075,"end_ag_acres":139944.179107543,"gross_loss_acres":4411.64650693884,"gross_gain_acres":209.49594240744,"net_loss_acres":4202.1505645314,"lost_to_development_acres":3905.03105385588,"share_loss_to_development":0.885164087311589,"net_loss_rate":0.0291519775362375,"loss_to_dev21_acres":3016.11886510584,"loss_to_dev22_acres":601.5780511806,"loss_to_dev23_acres":210.38552178072,"loss_to_dev24_acres":76.94861578872,"loss_to_grass71_acres":1.77915874656,"loss_to_other_acres":504.8362943364},{"region_id":"county:39167","region_type":"county","geoid":39167,"name":"Washington County","begin_year":1986,"end_year":1992,"begin_ag_acres":87896.669135677,"end_ag_acres":87434.7550461013,"gross_loss_acres":1599.46371315744,"gross_gain_acres":1137.5496235818,"net_loss_acres":461.91408957564,"lost_to_development_acres":539.52988989432,"share_loss_to_development":0.337319243604004,"net_loss_rate":0.00525519447002743,"loss_to_dev21_acres":450.349557723,"loss_to_dev22_acres":69.16479627252,"loss_to_dev23_acres":19.34835136884,"loss_to_dev24_acres":0.66718452996,"loss_to_grass71_acres":6.89424014292,"loss_to_other_acres":1053.0395831202},{"region_id":"county:39169","region_type":"county","geoid":39169,"name":"Wayne County","begin_year":1986,"end_year":1992,"begin_ag_acres":245012.843675331,"end_ag_acres":243008.176557644,"gross_loss_acres":2480.36968754796,"gross_gain_acres":475.70256986148,"net_loss_acres":2004.66711768648,"lost_to_development_acres":1758.0312364446,"share_loss_to_development":0.708777907289519,"net_loss_rate":0.00818188584571872,"loss_to_dev21_acres":1364.3923637682,"loss_to_dev22_acres":293.5611931824,"loss_to_dev23_acres":86.51159405148,"loss_to_dev24_acres":13.56608544252,"loss_to_grass71_acres":0.22239484332,"loss_to_other_acres":722.11605626004},{"region_id":"county:39171","region_type":"county","geoid":39171,"name":"Williams County","begin_year":1986,"end_year":1992,"begin_ag_acres":208270.76921559,"end_ag_acres":206574.563745589,"gross_loss_acres":1994.65934973708,"gross_gain_acres":298.45387973544,"net_loss_acres":1696.20547000164,"lost_to_development_acres":958.5217747092,"share_loss_to_development":0.48054409633181,"net_loss_rate":0.00814423203212844,"loss_to_dev21_acres":543.7553919174,"loss_to_dev22_acres":340.04171543628,"loss_to_dev23_acres":62.93774065956,"loss_to_dev24_acres":11.78692669596,"loss_to_grass71_acres":3.11352780648,"loss_to_other_acres":1033.0240472214},{"region_id":"county:39173","region_type":"county","geoid":39173,"name":"Wood County","begin_year":1986,"end_year":1992,"begin_ag_acres":320373.782677589,"end_ag_acres":316838.816643018,"gross_loss_acres":3764.92230256428,"gross_gain_acres":229.95626799288,"net_loss_acres":3534.9660345714,"lost_to_development_acres":2962.96649755236,"share_loss_to_development":0.786992734361156,"net_loss_rate":0.0110338805036642,"loss_to_dev21_acres":1456.01903921604,"loss_to_dev22_acres":1267.42821208068,"loss_to_dev23_acres":202.60170226452,"loss_to_dev24_acres":36.91754399112,"loss_to_grass71_acres":17.56919262228,"loss_to_other_acres":784.38661238964},{"region_id":"county:39175","region_type":"county","geoid":39175,"name":"Wyandot County","begin_year":1986,"end_year":1992,"begin_ag_acres":211300.454166139,"end_ag_acres":210501.834283776,"gross_loss_acres":1117.97887736964,"gross_gain_acres":319.35899500752,"net_loss_acres":798.61988236212,"lost_to_development_acres":556.43189798664,"share_loss_to_development":0.497712353292222,"net_loss_rate":0.00377954645442547,"loss_to_dev21_acres":394.30605720636,"loss_to_dev22_acres":134.5488802086,"loss_to_dev23_acres":25.13061729516,"loss_to_dev24_acres":2.44634327652,"loss_to_grass71_acres":2.00155358988,"loss_to_other_acres":559.54542579312}]
